spsim/__init__.py
spsim/__main__.py
spsim/phrase.py
spsim/spsim.py
spsim-0.1.2.dist-info/DESCRIPTION.rst
spsim-0.1.2.dist-info/METADATA
spsim-0.1.2.dist-info/RECORD
spsim-0.1.2.dist-info/WHEEL
spsim-0.1.2.dist-info/entry_points.txt
spsim-0.1.2.dist-info/metadata.json
spsim-0.1.2.dist-info/top_level.txt
