Metadata-Version: 2.0
Name: spsim
Version: 0.1.2
Summary: A spelling similarity measure for cognate identification.
Home-page: https://github.com/luismsgomes/spsim
Author: Luís Gomes
Author-email: luismsgomes@gmail.com
License: MIT
Keywords: text bilingual cognate mt machine translation
Platform: UNKNOWN
Classifier: Development Status :: 3 - Alpha
Classifier: License :: OSI Approved :: MIT License
Classifier: Programming Language :: Python :: 3.5
Classifier: Topic :: Text Processing :: Linguistic
Requires-Dist: docopt
Requires-Dist: munkres
Requires-Dist: openfile
Requires-Dist: stringology
